syntaxedit/__init__.py
syntaxedit/core.py
syntaxedit/highlightslot.py
syntaxedit-0.3.0.dist-info/METADATA
syntaxedit-0.3.0.dist-info/WHEEL
syntaxedit-0.3.0.dist-info/LICENSE
syntaxedit-0.3.0.dist-info/RECORD
